{"note":"This file is an internal implementation detail to speed up HTML report generation. Its format can change at any time. You might be looking for the JSON report: https://coverage.rtfd.io/cmd.html#cmd-json","format":5,"version":"7.8.0","globals":"f5aaee67ec885612188482ddcfbc0b53","files":{"z_cfb6adc3f81c8e3c___init___py":{"hash":"3c77fc9ef7f887ac2508d4109cf92472","index":{"url":"z_cfb6adc3f81c8e3c___init___py.html","file":"app/api/__init__.py","description":"","nums":{"precision":0,"n_files":1,"n_statements":0,"n_excluded":0,"n_missing":0,"n_branches":0,"n_partial_branches":0,"n_missing_branches":0}}},"z_c2f2d505d7a887a6___init___py":{"hash":"3c77fc9ef7f887ac2508d4109cf92472","index":{"url":"z_c2f2d505d7a887a6___init___py.html","file":"app/api/endpoints/__init__.py","description":"","nums":{"precision":0,"n_files":1,"n_statements":0,"n_excluded":0,"n_missing":0,"n_branches":0,"n_partial_branches":0,"n_missing_branches":0}}},"z_c2f2d505d7a887a6_exams_py":{"hash":"3178354b4fa781145161a7cbd39ca0a3","index":{"url":"z_c2f2d505d7a887a6_exams_py.html","file":"app/api/endpoints/exams.py","description":"","nums":{"precision":0,"n_files":1,"n_statements":63,"n_excluded":0,"n_missing":16,"n_branches":0,"n_partial_branches":0,"n_missing_branches":0}}},"z_c2f2d505d7a887a6_submissions_py":{"hash":"299021e9191527afd06e0e8e572bb32b","index":{"url":"z_c2f2d505d7a887a6_submissions_py.html","file":"app/api/endpoints/submissions.py","description":"","nums":{"precision":0,"n_files":1,"n_statements":187,"n_excluded":0,"n_missing":81,"n_branches":0,"n_partial_branches":0,"n_missing_branches":0}}},"z_c2f2d505d7a887a6_tasks_py":{"hash":"fe1b13d59a3e3ee020f392d11c38cef6","index":{"url":"z_c2f2d505d7a887a6_tasks_py.html","file":"app/api/endpoints/tasks.py","description":"","nums":{"precision":0,"n_files":1,"n_statements":63,"n_excluded":0,"n_missing":16,"n_branches":0,"n_partial_branches":0,"n_missing_branches":0}}},"z_cfb6adc3f81c8e3c_router_py":{"hash":"8f34b631badaf10fb945e6f164c75ec3","index":{"url":"z_cfb6adc3f81c8e3c_router_py.html","file":"app/api/router.py","description":"","nums":{"precision":0,"n_files":1,"n_statements":6,"n_excluded":0,"n_missing":0,"n_branches":0,"n_partial_branches":0,"n_missing_branches":0}}},"z_8f7e1016f2d37417_auth_py":{"hash":"81d2d20bf4ec5c4065ed622f29a9221c","index":{"url":"z_8f7e1016f2d37417_auth_py.html","file":"app/core/auth.py","description":"","nums":{"precision":0,"n_files":1,"n_statements":48,"n_excluded":0,"n_missing":8,"n_branches":0,"n_partial_branches":0,"n_missing_branches":0}}},"z_395c4f306d1419cf___init___py":{"hash":"3c77fc9ef7f887ac2508d4109cf92472","index":{"url":"z_395c4f306d1419cf___init___py.html","file":"app/db/__init__.py","description":"","nums":{"precision":0,"n_files":1,"n_statements":0,"n_excluded":0,"n_missing":0,"n_branches":0,"n_partial_branches":0,"n_missing_branches":0}}},"z_395c4f306d1419cf_mongodb_py":{"hash":"a285d3c48ec079a8d17794732dff6630","index":{"url":"z_395c4f306d1419cf_mongodb_py.html","file":"app/db/mongodb.py","description":"","nums":{"precision":0,"n_files":1,"n_statements":33,"n_excluded":0,"n_missing":8,"n_branches":0,"n_partial_branches":0,"n_missing_branches":0}}},"z_5f5a17c013354698_main_py":{"hash":"fe874e1c9878f7800fa6bc4d11ede79e","index":{"url":"z_5f5a17c013354698_main_py.html","file":"app/main.py","description":"","nums":{"precision":0,"n_files":1,"n_statements":19,"n_excluded":0,"n_missing":0,"n_branches":0,"n_partial_branches":0,"n_missing_branches":0}}},"z_6c0e4b930745278b___init___py":{"hash":"3c77fc9ef7f887ac2508d4109cf92472","index":{"url":"z_6c0e4b930745278b___init___py.html","file":"app/models/__init__.py","description":"","nums":{"precision":0,"n_files":1,"n_statements":0,"n_excluded":0,"n_missing":0,"n_branches":0,"n_partial_branches":0,"n_missing_branches":0}}},"z_6c0e4b930745278b_exam_py":{"hash":"06486b78cef320accfc3930ea48ab09c","index":{"url":"z_6c0e4b930745278b_exam_py.html","file":"app/models/exam.py","description":"","nums":{"precision":0,"n_files":1,"n_statements":57,"n_excluded":0,"n_missing":4,"n_branches":0,"n_partial_branches":0,"n_missing_branches":0}}},"z_6c0e4b930745278b_submission_py":{"hash":"e134806f0f88c87579d2d826947e4b62","index":{"url":"z_6c0e4b930745278b_submission_py.html","file":"app/models/submission.py","description":"","nums":{"precision":0,"n_files":1,"n_statements":34,"n_excluded":0,"n_missing":0,"n_branches":0,"n_partial_branches":0,"n_missing_branches":0}}},"z_6c0e4b930745278b_task_py":{"hash":"a9da74bc11439fcd2f10f6be3d0494c5","index":{"url":"z_6c0e4b930745278b_task_py.html","file":"app/models/task.py","description":"","nums":{"precision":0,"n_files":1,"n_statements":45,"n_excluded":0,"n_missing":1,"n_branches":0,"n_partial_branches":0,"n_missing_branches":0}}},"z_6c0e4b930745278b_user_py":{"hash":"1b486040b6bcbd05ab70871453d55bdc","index":{"url":"z_6c0e4b930745278b_user_py.html","file":"app/models/user.py","description":"","nums":{"precision":0,"n_files":1,"n_statements":16,"n_excluded":0,"n_missing":0,"n_branches":0,"n_partial_branches":0,"n_missing_branches":0}}},"z_4eed7ad336a4b97f___init___py":{"hash":"3c77fc9ef7f887ac2508d4109cf92472","index":{"url":"z_4eed7ad336a4b97f___init___py.html","file":"app/repositories/__init__.py","description":"","nums":{"precision":0,"n_files":1,"n_statements":0,"n_excluded":0,"n_missing":0,"n_branches":0,"n_partial_branches":0,"n_missing_branches":0}}},"z_4eed7ad336a4b97f_exam_repository_py":{"hash":"14abab4fd081b7f27c5af4aa686d9171","index":{"url":"z_4eed7ad336a4b97f_exam_repository_py.html","file":"app/repositories/exam_repository.py","description":"","nums":{"precision":0,"n_files":1,"n_statements":68,"n_excluded":0,"n_missing":19,"n_branches":0,"n_partial_branches":0,"n_missing_branches":0}}},"z_4eed7ad336a4b97f_task_repository_py":{"hash":"c33057378e8f4cf1e54ee8b2b20c4558","index":{"url":"z_4eed7ad336a4b97f_task_repository_py.html","file":"app/repositories/task_repository.py","description":"","nums":{"precision":0,"n_files":1,"n_statements":68,"n_excluded":0,"n_missing":21,"n_branches":0,"n_partial_branches":0,"n_missing_branches":0}}},"z_4eed7ad336a4b97f_user_repository_py":{"hash":"66a2022d577de9d2bc0faa1815653bf9","index":{"url":"z_4eed7ad336a4b97f_user_repository_py.html","file":"app/repositories/user_repository.py","description":"","nums":{"precision":0,"n_files":1,"n_statements":90,"n_excluded":0,"n_missing":14,"n_branches":0,"n_partial_branches":0,"n_missing_branches":0}}},"z_c318f3fa19a49f69___init___py":{"hash":"3c77fc9ef7f887ac2508d4109cf92472","index":{"url":"z_c318f3fa19a49f69___init___py.html","file":"app/services/__init__.py","description":"","nums":{"precision":0,"n_files":1,"n_statements":0,"n_excluded":0,"n_missing":0,"n_branches":0,"n_partial_branches":0,"n_missing_branches":0}}},"z_c318f3fa19a49f69_exam_service_py":{"hash":"e795c4bb60bf6dd6fd8f20cda054bb4a","index":{"url":"z_c318f3fa19a49f69_exam_service_py.html","file":"app/services/exam_service.py","description":"","nums":{"precision":0,"n_files":1,"n_statements":51,"n_excluded":0,"n_missing":11,"n_branches":0,"n_partial_branches":0,"n_missing_branches":0}}},"z_c318f3fa19a49f69_submission_service_py":{"hash":"9eff573f5285c600d283233202200156","index":{"url":"z_c318f3fa19a49f69_submission_service_py.html","file":"app/services/submission_service.py","description":"","nums":{"precision":0,"n_files":1,"n_statements":178,"n_excluded":0,"n_missing":40,"n_branches":0,"n_partial_branches":0,"n_missing_branches":0}}},"z_c318f3fa19a49f69_task_service_py":{"hash":"b579a6909e63e7f64502dca67d396ca5","index":{"url":"z_c318f3fa19a49f69_task_service_py.html","file":"app/services/task_service.py","description":"","nums":{"precision":0,"n_files":1,"n_statements":51,"n_excluded":0,"n_missing":12,"n_branches":0,"n_partial_branches":0,"n_missing_branches":0}}}}}