{"note":"This file is an internal implementation detail to speed up HTML report generation. Its format can change at any time. You might be looking for the JSON report: https://coverage.rtfd.io/cmd.html#cmd-json","format":5,"version":"7.8.0","globals":"b982419b62df3d0f053172127641ee3f","files":{"z_5f5a17c013354698_main_py":{"hash":"8b6e0bd7f07025350a8909eb932dddc3","index":{"url":"z_5f5a17c013354698_main_py.html","file":"app/main.py","description":"","nums":{"precision":0,"n_files":1,"n_statements":5,"n_excluded":0,"n_missing":0,"n_branches":0,"n_partial_branches":0,"n_missing_branches":0}}},"z_a44f0ac069e85531_test_get_health_py":{"hash":"305bec726f04b95c776a26e9ae7c93eb","index":{"url":"z_a44f0ac069e85531_test_get_health_py.html","file":"tests/test_get_health.py","description":"","nums":{"precision":0,"n_files":1,"n_statements":8,"n_excluded":0,"n_missing":0,"n_branches":0,"n_partial_branches":0,"n_missing_branches":0}}}}}