{"note":"This file is an internal implementation detail to speed up HTML report generation. Its format can change at any time. You might be looking for the JSON report: https://coverage.rtfd.io/cmd.html#cmd-json","format":5,"version":"7.8.0","globals":"faadcaf9953a2226ed18046249976a25","files":{"z_8f7e1016f2d37417_auth_py":{"hash":"b48d12992adaa95cbe4264f1cd9b97cd","index":{"url":"z_8f7e1016f2d37417_auth_py.html","file":"app/core/auth.py","description":"","nums":{"precision":0,"n_files":1,"n_statements":37,"n_excluded":0,"n_missing":11,"n_branches":0,"n_partial_branches":0,"n_missing_branches":0}}},"z_8f7e1016f2d37417_config_py":{"hash":"aa5565df7027e59be5d32f508f5da988","index":{"url":"z_8f7e1016f2d37417_config_py.html","file":"app/core/config.py","description":"","nums":{"precision":0,"n_files":1,"n_statements":11,"n_excluded":0,"n_missing":0,"n_branches":0,"n_partial_branches":0,"n_missing_branches":0}}},"z_5f5a17c013354698_main_py":{"hash":"754c572a0123bceb37fec4f1d67b6e1b","index":{"url":"z_5f5a17c013354698_main_py.html","file":"app/main.py","description":"","nums":{"precision":0,"n_files":1,"n_statements":50,"n_excluded":0,"n_missing":28,"n_branches":0,"n_partial_branches":0,"n_missing_branches":0}}},"z_4eed7ad336a4b97f_user_repository_py":{"hash":"10096843954167a0c02799110d37f1d7","index":{"url":"z_4eed7ad336a4b97f_user_repository_py.html","file":"app/repositories/user_repository.py","description":"","nums":{"precision":0,"n_files":1,"n_statements":28,"n_excluded":0,"n_missing":3,"n_branches":0,"n_partial_branches":0,"n_missing_branches":0}}},"z_6549c0330f733809_user_router_py":{"hash":"07ea3e7c7be73d8f2cfcd92fe53dd36c","index":{"url":"z_6549c0330f733809_user_router_py.html","file":"app/routers/user_router.py","description":"","nums":{"precision":0,"n_files":1,"n_statements":17,"n_excluded":0,"n_missing":9,"n_branches":0,"n_partial_branches":0,"n_missing_branches":0}}},"z_c0f67d75e686303c_user_py":{"hash":"00f041aecc290d0e1443b300b89f3b9b","index":{"url":"z_c0f67d75e686303c_user_py.html","file":"app/schemas/user.py","description":"","nums":{"precision":0,"n_files":1,"n_statements":13,"n_excluded":0,"n_missing":1,"n_branches":0,"n_partial_branches":0,"n_missing_branches":0}}},"z_c318f3fa19a49f69_user_profile_py":{"hash":"44390bf9298803a117fa30856b70df54","index":{"url":"z_c318f3fa19a49f69_user_profile_py.html","file":"app/services/user_profile.py","description":"","nums":{"precision":0,"n_files":1,"n_statements":12,"n_excluded":0,"n_missing":7,"n_branches":0,"n_partial_branches":0,"n_missing_branches":0}}},"z_748a0465d46c2a16_problem_details_py":{"hash":"57b9458fb06c9b32ad700b67111f9449","index":{"url":"z_748a0465d46c2a16_problem_details_py.html","file":"app/utils/problem_details.py","description":"","nums":{"precision":0,"n_files":1,"n_statements":5,"n_excluded":0,"n_missing":2,"n_branches":0,"n_partial_branches":0,"n_missing_branches":0}}},"z_a44f0ac069e85531_test_edit_profile_py":{"hash":"5024aeac508797faf1dc2e52b77719c8","index":{"url":"z_a44f0ac069e85531_test_edit_profile_py.html","file":"tests/test_edit_profile.py","description":"","nums":{"precision":0,"n_files":1,"n_statements":62,"n_excluded":0,"n_missing":0,"n_branches":0,"n_partial_branches":0,"n_missing_branches":0}}},"z_a44f0ac069e85531_test_get_health_py":{"hash":"305bec726f04b95c776a26e9ae7c93eb","index":{"url":"z_a44f0ac069e85531_test_get_health_py.html","file":"tests/test_get_health.py","description":"","nums":{"precision":0,"n_files":1,"n_statements":8,"n_excluded":0,"n_missing":0,"n_branches":0,"n_partial_branches":0,"n_missing_branches":0}}}}}